vtx_protocol/__init__.py
vtx_protocol/generated/componentize_py_runtime.pyi
vtx_protocol/generated/componentize_py_types.py
vtx_protocol/generated/poll_loop.py
vtx_protocol/generated/componentize_py_async_support/__init__.py
vtx_protocol/generated/componentize_py_async_support/futures.py
vtx_protocol/generated/componentize_py_async_support/streams.py
vtx_protocol/generated/wit_world/__init__.py
vtx_protocol/generated/wit_world/imports/__init__.py
vtx_protocol/generated/wit_world/imports/vtx_auth_types.py
vtx_protocol/generated/wit_world/imports/vtx_context.py
vtx_protocol/generated/wit_world/imports/vtx_event_bus.py
vtx_protocol/generated/wit_world/imports/vtx_events.py
vtx_protocol/generated/wit_world/imports/vtx_ffmpeg.py
vtx_protocol/generated/wit_world/imports/vtx_http_client.py
vtx_protocol/generated/wit_world/imports/vtx_sql.py
vtx_protocol/generated/wit_world/imports/vtx_types.py
vtx_protocol/generated/wit_world/imports/vtx_vfs.py
vtx_protocol/wit/vtx.wit
vtx_protocol-4.0.0.dist-info/METADATA
vtx_protocol-4.0.0.dist-info/WHEEL
vtx_protocol-4.0.0.dist-info/top_level.txt
vtx_protocol-4.0.0.dist-info/RECORD
