Metadata-Version: 2.4
Name: vtx-protocol
Version: 4.0.0
Summary: WIT interface definitions for VTX plugins
Requires-Python: >=3.10
